android_widgets/__init__.py
android_widgets/aw_logging.py
android_widgets/config.py
android_widgets/facade.py
android_widgets/java_classes.py
android_widgets/maker.py
android_widgets/tools.py
android_widgets-0.1.5.dist-info/METADATA
android_widgets-0.1.5.dist-info/WHEEL
android_widgets-0.1.5.dist-info/top_level.txt
android_widgets-0.1.5.dist-info/RECORD
