Metadata-Version: 2.4
Name: android-widgets
Version: 0.1.5
Summary: This would be used to auto gen XMLs for Android Home Screen widgets.
Author-email: Fabian <fector101@yahoo.com>
License-Expression: MIT
Project-URL: Homepage, https://github.com/Fector101/kivy-androidwidgets
Project-URL: Documentation, https://github.com/Fector101/kivy-androidwidgets
Project-URL: Source, https://github.com/Fector101/kivy-androidwidgets
Project-URL: Tracker, https://github.com/Fector101/kivy-androidwidgets/issues
Keywords: kivy,android,widgets,hello-world,python-package
Classifier: Programming Language :: Python :: 3
Classifier: Operating System :: Android
Classifier: Development Status :: 3 - Alpha
Classifier: Intended Audience :: Developers
Classifier: Topic :: Software Development :: Libraries :: Python Modules
Requires-Python: >=3.7
Requires-Dist: kivy>=2.0.0
